Metadata-Version: 2.1
Name: poll_extractor
Version: 1.1.1
Summary: A light python library that helps to make charts
Author-email: andreyfakerare@gmail.com
